{"uin":"HH9154-10-0001-000","tep":[{"name":"Высота объекта","val":"41","unit":"Метр"},{"name":"Количество машино-мест","val":"194","unit":"Машино-место"},{"name":"Площадь наземных этажей объекта","val":"37359","unit":"Квадратный метр"},{"name":"Общая площадь объекта","val":"37359","unit":"Квадратный метр"},{"name":"Площадь жилых помещений объекта, в том числе: общая площадь квартир (без учета балконов и лоджий)","val":"23355","unit":"Квадратный метр"}],"schedule":{"startPlan":null,"startFact":null,"inputPlan":"2031-12-31","inputFact":null}}